dswizard/core/__init__.py
dswizard/core/base_bandit_learner.py
dswizard/core/base_config_generator.py
dswizard/core/base_iteration.py
dswizard/core/base_structure_generator.py
dswizard/core/config_cache.py
dswizard/core/dispatcher.py
dswizard/core/ensemble.py
dswizard/core/logger.py
dswizard/core/master.py
dswizard/core/model.py
dswizard/core/runhistory.py
dswizard/core/similaritystore.py
dswizard/core/worker.py
dswizard/optimizers/__init__.py
dswizard/optimizers/bandit_learners/__init__.py
dswizard/optimizers/bandit_learners/hyperband.py
dswizard/optimizers/bandit_learners/pseudo.py
dswizard/optimizers/config_generators/__init__.py
dswizard/optimizers/config_generators/hyperopt.py
dswizard/optimizers/config_generators/random_sampling.py
dswizard/optimizers/config_generators/smac_generator.py
dswizard/optimizers/iterations/__init__.py
dswizard/optimizers/iterations/pseudo.py
dswizard/optimizers/iterations/successivehalving.py
dswizard/optimizers/iterations/successiveresampling.py
dswizard/optimizers/structure_generators/__init__.py
dswizard/optimizers/structure_generators/fixed.py
dswizard/optimizers/structure_generators/mcts.py
dswizard/optimizers/structure_generators/random_search.py
dswizard/pipeline/__init__.py
dswizard/pipeline/constants.py
dswizard/pipeline/pipeline.py
dswizard/pipeline/voting_ensemble.py
dswizard/util/__init__.py
dswizard/util/autoproxy.py
dswizard/util/search_space.py
dswizard/util/util.py
dswizard/workers/__init__.py
dswizard/workers/sklearn_worker.py
dswizard-0.1.0.dist-info/LICENSE
dswizard-0.1.0.dist-info/METADATA
dswizard-0.1.0.dist-info/WHEEL
dswizard-0.1.0.dist-info/top_level.txt
dswizard-0.1.0.dist-info/RECORD
