Metadata-Version: 2.1
Name: dswizard
Version: 0.1.0
Summary: DataScience Wizard for automatic assembly of machine learning pipelines
Home-page: https://github.com/Ennosigaeon/dswizard
Author: Marc Zoeller
Author-email: m.zoeller@usu.de
License: MIT
Keywords: automl,machine learning,pipeline synthesis
Platform: UNKNOWN
Classifier: License :: OSI Approved :: MIT License
Classifier: Programming Language :: Python :: 3
Classifier: Programming Language :: Python :: 3.5
Requires-Python: >=3.5
Requires-Dist: ConfigSpace (==0.4.*)
Requires-Dist: matplotlib (==3.1.*)
Requires-Dist: networkx (==2.3)
Requires-Dist: numpy (==1.19.*)
Requires-Dist: pandas (==1.1.*)
Requires-Dist: scikit-learn (==0.23.*)
Requires-Dist: scipy (==1.5.*)
Requires-Dist: openml (==0.10.*)
Requires-Dist: multiprocessing-logging (==0.3.*)
Requires-Dist: dswizard-components (==0.1.*)
